lpbio/__init__.py
lpbio/scripts/__init__.py
lpbio/scripts/logger.py
lpbio/scripts/prokka_script.py
lpbio/scripts/parsers/__init__.py
lpbio/scripts/parsers/prokka_parser.py
lpbio/swarm/Swarm.py
lpbio/swarm/__init__.py
lpbio-0.1.0a0.data/scripts/bulk_prokka
lpbio-0.1.0a0.dist-info/METADATA
lpbio-0.1.0a0.dist-info/RECORD
lpbio-0.1.0a0.dist-info/WHEEL
lpbio-0.1.0a0.dist-info/top_level.txt
pysge/Job.py
pysge/JobGroup.py
pysge/__init__.py
