Metadata-Version: 2.1
Name: lpbio
Version: 0.1.0a0
Summary: lpbio provides scripts and modules for computational biology
Home-page: http://widdowquinn.github.io/lpbio/
Author: Leighton Pritchard
Author-email: leighton.pritchard@hutton.ac.uk
License: MIT
Download-URL: https://github.com/widdowquinn/lpbio/releases
Keywords: genome bioinformatics sequence
Platform: Posix; MacOS X
Classifier: Development Status :: 4 - Beta
Classifier: Environment :: Console
Classifier: Intended Audience :: Science/Research
Classifier: License :: OSI Approved :: MIT License
Classifier: Natural Language :: English
Classifier: Operating System :: MacOS :: MacOS X
Classifier: Operating System :: POSIX :: Linux
Classifier: Programming Language :: Python
Classifier: Programming Language :: Python :: 3
Classifier: Programming Language :: Python :: 3.5
Classifier: Programming Language :: Python :: 3.6
Classifier: Programming Language :: Python :: 3.7
Classifier: Topic :: Scientific/Engineering :: Bio-Informatics
